mrsphinxjson/__init__.py
mrsphinxjson/_version.py
mrsphinxjson-0.1.1.dist-info/LICENSE
mrsphinxjson-0.1.1.dist-info/METADATA
mrsphinxjson-0.1.1.dist-info/WHEEL
mrsphinxjson-0.1.1.dist-info/top_level.txt
mrsphinxjson-0.1.1.dist-info/RECORD
