Metadata-Version: 2.1
Name: mrsphinxjson
Version: 0.1.1
Summary: Sphinx extension to include JSON-files in the documentation.
Home-page: https://gitlab.com/anatas_ch/pyl_mrsphinxjson
Author: Michael Rippstein
Author-email: info@anatas.ch
License: AGPL-3.0
Project-URL: Bug Tracker, https://gitlab.com/anatas_ch/pyl_mrsphinxjson/-/issues
Project-URL: Source Code, https://gitlab.com/anatas_ch/pyl_mrsphinxjson
Platform: UNKNOWN
Classifier: Development Status :: 3 - Alpha
Classifier: Programming Language :: Python :: 3
Classifier: Environment :: Console
Classifier: Environment :: Web Environment
Classifier: Framework :: Sphinx :: Extension
Classifier: Intended Audience :: Developers
Classifier: License :: OSI Approved :: GNU Affero General Public License v3 or later (AGPLv3+)
Classifier: Operating System :: OS Independent
Classifier: Topic :: Documentation
Classifier: Topic :: Utilities
Requires-Python: >=3.9
License-File: LICENSE
Requires-Dist: Sphinx (>=4.2.0)
